noisebase/__init__.py
noisebase/compression.py
noisebase/data.py
noisebase/projective.py
noisebase/conf/noisebase/sampleset_test32_v1.yaml
noisebase/conf/noisebase/sampleset_test8_v1.yaml
noisebase/conf/noisebase/sampleset_v1.yaml
noisebase/conf/noisebase/format/test_sample_v1.yaml
noisebase/conf/noisebase/format/training_sample_v1.yaml
noisebase/lightning/__init__.py
noisebase/lightning/midepoch_ckpt.py
noisebase/loaders/__init__.py
noisebase/loaders/lightning/__init__.py
noisebase/loaders/lightning/training_sample_v1.py
noisebase/loaders/torch/__init__.py
noisebase/loaders/torch/test_sample_v1.py
noisebase/loaders/torch/training_sample_v1.py
noisebase/metrics/__init__.py
noisebase/metrics/flip.py
noisebase/metrics/fvvdp.py
noisebase/scripts/__init__.py
noisebase/scripts/nb_compute_metrics.py
noisebase/scripts/nb_download.py
noisebase/scripts/nb_result_table.py
noisebase/scripts/nb_save_reference.py
noisebase/torch/__init__.py
noisebase/torch/misc.py
noisebase/torch/projective.py
noisebase/torch/video_sampler.py
noisebase-1.1.1.dist-info/LICENSE
noisebase-1.1.1.dist-info/METADATA
noisebase-1.1.1.dist-info/WHEEL
noisebase-1.1.1.dist-info/entry_points.txt
noisebase-1.1.1.dist-info/top_level.txt
noisebase-1.1.1.dist-info/RECORD
