Metadata-Version: 2.1
Name: noisebase
Version: 1.1.1
Summary: Datasets and benchmarks for neural Monte Carlo denoising
Author-email: Martin Bálint <martin@balint.io>
Project-URL: Documentation, https://balint.io/noisebase
Project-URL: Repository, https://github.com/balintio/noisebase.git
Keywords: denoising,Monte Carlo,MC,neural
Classifier: Development Status :: 4 - Beta
Classifier: License :: OSI Approved :: Apache Software License
Classifier: Environment :: GPU
Classifier: Operating System :: OS Independent
Classifier: Programming Language :: Python :: 3
License-File: LICENSE
Requires-Dist: torch
Requires-Dist: pyfvvdp ==1.2.0
Requires-Dist: zarr >=2
Requires-Dist: pytorch-msssim
Requires-Dist: hydra-core
Requires-Dist: requests
Requires-Dist: tqdm
